LICENSE.md
README.md
setup.py
BAxUS.egg-info/PKG-INFO
BAxUS.egg-info/SOURCES.txt
BAxUS.egg-info/dependency_links.txt
BAxUS.egg-info/entry_points.txt
BAxUS.egg-info/requires.txt
BAxUS.egg-info/top_level.txt
baxus/__init__.py
baxus/baxus.py
baxus/benchmark_runner.py
baxus/embeddedturbo.py
baxus/gp.py
baxus/benchmarks/__init__.py
baxus/benchmarks/benchmark_function.py
baxus/benchmarks/benchmark_utils.py
baxus/benchmarks/other_methods.py
baxus/benchmarks/real_world_benchmarks.py
baxus/benchmarks/synthetic_benchmark_functions.py
baxus/util/__init__.py
baxus/util/acquisition_function_types.py
baxus/util/acquisition_functions.py
baxus/util/console_entry_point.py
baxus/util/data_utils.py
baxus/util/exceptions.py
baxus/util/gp_utils.py
baxus/util/parsing.py
baxus/util/projections.py
baxus/util/utils.py
baxus/util/behaviors/__init__.py
baxus/util/behaviors/baxus_configuration.py
baxus/util/behaviors/embedded_turbo_configuration.py
baxus/util/behaviors/embedding_configuration.py
baxus/util/behaviors/gp_configuration.py
baxus/util/space_learning/__init__.py
baxus/util/space_learning/trust_region.py
tests/__init__.py
tests/test_benchmark_function.py
tests/test_benchmark_runner.py
tests/test_hesbo.py
tests/test_synthetic_benchmark_functions.py
tests/text_adaturbo_1.py
tests/text_gp.py