Metadata-Version: 2.1
Name: BAxUS
Version: 0.0.8
Author: Leonard Papenmeier
Author-email: leonard.papenmeier@cs.lth.se
License-File: LICENSE.md
